LICENSE.txt
MANIFEST.in
README.rst
setup.cfg
setup.py
Hotel_Lite/Conexion.py
Hotel_Lite/Eventos.py
Hotel_Lite/Facturacion.py
Hotel_Lite/FuncionesCli.py
Hotel_Lite/FuncionesCompresion.py
Hotel_Lite/FuncionesGenericas.py
Hotel_Lite/FuncionesHab.py
Hotel_Lite/FuncionesIm.py
Hotel_Lite/FuncionesImportExport.py
Hotel_Lite/FuncionesRes.py
Hotel_Lite/FuncionesServicios.py
Hotel_Lite/Variables.py
Hotel_Lite/empresa.sqlite
Hotel_Lite/estilos.css
Hotel_Lite/main.py
Hotel_Lite/ventana.glade
Hotel_Lite/ventana2.glade
Hotel_Lite.egg-info/PKG-INFO
Hotel_Lite.egg-info/SOURCES.txt
Hotel_Lite.egg-info/dependency_links.txt
Hotel_Lite.egg-info/top_level.txt