Metadata-Version: 1.1
Name: Hotel-Lite
Version: 0.6
Summary: Gestor sencillo de un hotel o casa rural
Home-page: https://github.com/MrNadix/HOTEL_Lite
Author: a13franciscoca
Author-email: francasal.34@gmail.com
License: Copyright <YEAR> <COPYRIGHT HOLDER>
